compas_model/__init__.py
compas_model/errors.py
compas_model/algorithms/__init__.py
compas_model/algorithms/collision.py
compas_model/algorithms/contacts.py
compas_model/datastructures/__init__.py
compas_model/datastructures/bvh.py
compas_model/datastructures/kdtree.py
compas_model/elements/__init__.py
compas_model/elements/beam.py
compas_model/elements/column.py
compas_model/elements/element.py
compas_model/elements/group.py
compas_model/elements/plate.py
compas_model/geometry/__init__.py
compas_model/geometry/bbox.py
compas_model/geometry/distances.py
compas_model/geometry/gjk2.py
compas_model/geometry/intersections.py
compas_model/geometry/minkowski2.py
compas_model/geometry/minkowski3.py
compas_model/interactions/__init__.py
compas_model/interactions/contact.py
compas_model/materials/__init__.py
compas_model/materials/concrete.py
compas_model/materials/errors.py
compas_model/materials/material.py
compas_model/materials/steel.py
compas_model/materials/timber.py
compas_model/models/__init__.py
compas_model/models/bvh.py
compas_model/models/elementtree.py
compas_model/models/interactiongraph.py
compas_model/models/model.py
compas_model/modifiers/__init__.py
compas_model/modifiers/modifier.py
compas_model/notebooks/__init__.py
compas_model/rhino/__init__.py
compas_model/scene/__init__.py
compas_model/scene/elementobject.py
compas_model/scene/modelobject.py
compas_model/viewer/__init__.py
compas_model/viewer/elementobject.py
compas_model/viewer/modelobject.py
compas_model-0.9.2.dist-info/licenses/LICENSE
compas_model-0.9.2.dist-info/METADATA
compas_model-0.9.2.dist-info/WHEEL
compas_model-0.9.2.dist-info/top_level.txt
compas_model-0.9.2.dist-info/RECORD
