Metadata-Version: 2.4
Name: compas_model
Version: 0.9.2
Summary: This package provides a universal model datastructure for design, analysis, fabrication, and construction of AEC objects.
Author-email: tom van mele <tom.v.mele@gmail.com>, petras vestartas <petrasvestartas@gmail.com>
License: MIT License
Project-URL: Homepage, https://blockresearchgroup.github.io/compas_model
Project-URL: Documentation, https://blockresearchgroup.github.io/compas_model
Project-URL: Repository, https://github.com/blockresearchgroup/compas_model.git
Project-URL: Changelog, https://github.com/blockresearchgroup/compas_model/blob/main/CHANGELOG.md
Keywords: bim,bam,bom
Classifier: Development Status :: 4 - Beta
Classifier: Topic :: Scientific/Engineering
Classifier: Programming Language :: Python
Classifier: Programming Language :: Python :: 3
Classifier: Programming Language :: Python :: 3.9
Classifier: Programming Language :: Python :: 3.10
Classifier: Programming Language :: Python :: 3.11
Requires-Python: >=3.9
License-File: LICENSE
Requires-Dist: compas>=2
Requires-Dist: shapely
Provides-Extra: dev
Requires-Dist: attrs>=17.4; extra == "dev"
Requires-Dist: black>=22.12.0; extra == "dev"
Requires-Dist: bump-my-version; extra == "dev"
Requires-Dist: compas_invocations2; extra == "dev"
Requires-Dist: invoke>=0.14; extra == "dev"
Requires-Dist: ruff; extra == "dev"
Requires-Dist: sphinx_compas2_theme; extra == "dev"
Requires-Dist: twine; extra == "dev"
Requires-Dist: wheel; extra == "dev"
Provides-Extra: viz
Requires-Dist: compas_notebook>=0.5.0; extra == "viz"
Requires-Dist: compas_viewer; extra == "viz"
Dynamic: license-file
